{"trial_id": "0260", "hyperparameters": {"space": [{"class_name": "Choice", "config": {"name": "activation", "default": "relu", "conditions": [], "values": ["relu", "tanh", "sigmoid", "leaky_relu"], "ordered": false}}, {"class_name": "Int", "config": {"name": "first_units", "default": null, "conditions": [], "min_value": 1, "max_value": 80, "step": 2, "sampling": "linear"}}, {"class_name": "Int", "config": {"name": "num_layers", "default": null, "conditions": [], "min_value": 1, "max_value": 10, "step": 1, "sampling": "linear"}}, {"class_name": "Int", "config": {"name": "units_0", "default": null, "conditions": [], "min_value": 1, "max_value": 80, "step": 2, "sampling": "linear"}}, {"class_name": "Int", "config": {"name": "units_1", "default": null, "conditions": [], "min_value": 1, "max_value": 80, "step": 2, "sampling": "linear"}}, {"class_name": "Int", "config": {"name": "units_2", "default": null, "conditions": [], "min_value": 1, "max_value": 80, "step": 2, "sampling": "linear"}}, {"class_name": "Int", "config": {"name": "units_3", "default": null, "conditions": [], "min_value": 1, "max_value": 80, "step": 2, "sampling": "linear"}}, {"class_name": "Int", "config": {"name": "units_4", "default": null, "conditions": [], "min_value": 1, "max_value": 80, "step": 2, "sampling": "linear"}}, {"class_name": "Int", "config": {"name": "units_5", "default": null, "conditions": [], "min_value": 1, "max_value": 80, "step": 2, "sampling": "linear"}}, {"class_name": "Int", "config": {"name": "units_6", "default": null, "conditions": [], "min_value": 1, "max_value": 80, "step": 2, "sampling": "linear"}}, {"class_name": "Int", "config": {"name": "units_7", "default": null, "conditions": [], "min_value": 1, "max_value": 80, "step": 2, "sampling": "linear"}}, {"class_name": "Int", "config": {"name": "units_8", "default": null, "conditions": [], "min_value": 1, "max_value": 80, "step": 2, "sampling": "linear"}}, {"class_name": "Int", "config": {"name": "units_9", "default": null, "conditions": [], "min_value": 1, "max_value": 80, "step": 2, "sampling": "linear"}}], "values": {"activation": "tanh", "first_units": 31, "num_layers": 4, "units_0": 39, "units_1": 75, "units_2": 63, "units_3": 67, "units_4": 19, "units_5": 37, "units_6": 65, "units_7": 79, "units_8": 73, "units_9": 73, "tuner/epochs": 7, "tuner/initial_epoch": 0, "tuner/bracket": 1, "tuner/round": 0}}, "metrics": {"metrics": {"loss": {"direction": "min", "observations": [{"value": [0.1880977600812912], "step": 6}]}, "accuracy": {"direction": "max", "observations": [{"value": [0.7285802960395813], "step": 6}]}, "val_loss": {"direction": "min", "observations": [{"value": [0.19009818136692047], "step": 6}]}, "val_accuracy": {"direction": "max", "observations": [{"value": [0.7240816354751587], "step": 6}]}}}, "score": 0.7240816354751587, "best_step": 6, "status": "COMPLETED", "message": null}